sellm.py
sellm-1.0.6.dist-info/licenses/LICENSE
sellm-1.0.6.dist-info/METADATA
sellm-1.0.6.dist-info/WHEEL
sellm-1.0.6.dist-info/entry_points.txt
sellm-1.0.6.dist-info/top_level.txt
sellm-1.0.6.dist-info/RECORD
